dimm_utils/__init__.py
dimm_utils/constants.py
dimm_utils/core.py
dimm_utils-0.1.5.dist-info/WHEEL
dimm_utils-0.1.5.dist-info/METADATA
dimm_utils-0.1.5.dist-info/RECORD
